Metadata-Version: 2.1
Name: torchx-applovin
Version: 0.6.0.dev12
Summary: TorchX SDK and Components
Home-page: https://github.com/pytorch/torchx
Author: TorchX Devs
Author-email: torchx@fb.com
License: BSD-3
Keywords: pytorch,machine learning,applovin
Classifier: Development Status :: 4 - Beta
Classifier: Intended Audience :: Developers
Classifier: Intended Audience :: Science/Research
Classifier: License :: OSI Approved :: BSD License
Classifier: Programming Language :: Python :: 3
Classifier: Programming Language :: Python :: 3.8
Classifier: Topic :: Scientific/Engineering :: Artificial Intelligence
Requires-Python: >=3.7
License-File: LICENSE
Requires-Dist: pyre-extensions
Requires-Dist: docstring-parser (==0.8.1)
Requires-Dist: importlib-metadata
Requires-Dist: pyyaml
Requires-Dist: docker
Requires-Dist: filelock
Requires-Dist: fsspec (==2023.1.0)
Requires-Dist: urllib3 (<1.27,>=1.21.1)
Requires-Dist: tabulate
Provides-Extra: dev
Requires-Dist: aiobotocore (==2.4.2) ; extra == 'dev'
Requires-Dist: ax-platform[mysql] (==0.2.3) ; extra == 'dev'
Requires-Dist: black (==23.3.0) ; extra == 'dev'
Requires-Dist: boto3 (==1.24.59) ; extra == 'dev'
Requires-Dist: captum (>=0.4.0) ; extra == 'dev'
Requires-Dist: flake8 (==3.9.0) ; extra == 'dev'
Requires-Dist: fsspec[s3] (==2023.1.0) ; extra == 'dev'
Requires-Dist: google-api-core ; extra == 'dev'
Requires-Dist: google-cloud-batch (>=0.5.0) ; extra == 'dev'
Requires-Dist: google-cloud-logging (>=3.0.0) ; extra == 'dev'
Requires-Dist: google-cloud-runtimeconfig (>=0.33.2) ; extra == 'dev'
Requires-Dist: hydra-core ; extra == 'dev'
Requires-Dist: ipython ; extra == 'dev'
Requires-Dist: kfp (==1.8.22) ; extra == 'dev'
Requires-Dist: mlflow-skinny ; extra == 'dev'
Requires-Dist: moto (==4.1.6) ; extra == 'dev'
Requires-Dist: protobuf (==3.20.3) ; extra == 'dev'
Requires-Dist: pyre-extensions ; extra == 'dev'
Requires-Dist: pyre-check ; extra == 'dev'
Requires-Dist: pytest ; extra == 'dev'
Requires-Dist: pytorch-lightning (==1.5.10) ; extra == 'dev'
Requires-Dist: torch-model-archiver (>=0.4.2) ; extra == 'dev'
Requires-Dist: torch (>=1.10.0) ; extra == 'dev'
Requires-Dist: torchmetrics (<0.11.0) ; extra == 'dev'
Requires-Dist: torchserve (>=0.4.2) ; extra == 'dev'
Requires-Dist: torchtext (>=0.11.0) ; extra == 'dev'
Requires-Dist: torchvision (>=0.11.1) ; extra == 'dev'
Requires-Dist: ts (==0.5.1) ; extra == 'dev'
Requires-Dist: usort (==1.0.2) ; extra == 'dev'
Requires-Dist: ray[default] ; extra == 'dev'
Provides-Extra: gcp_batch
Requires-Dist: google-cloud-batch (>=0.5.0) ; extra == 'gcp_batch'
Requires-Dist: google-cloud-logging (>=3.0.0) ; extra == 'gcp_batch'
Requires-Dist: google-cloud-runtimeconfig (>=0.33.2) ; extra == 'gcp_batch'
Provides-Extra: kfp
Requires-Dist: kfp (==1.6.2) ; extra == 'kfp'
Provides-Extra: kubernetes
Requires-Dist: kubernetes (>=11) ; extra == 'kubernetes'
Provides-Extra: ray
Requires-Dist: ray (>=1.12.1) ; extra == 'ray'
